nivora_ai/__init__.py
nivora_ai/py.typed
nivora_ai/api/__init__.py
nivora_ai/api/main.py
nivora_ai/api/websocket.py
nivora_ai/api/routes/__init__.py
nivora_ai/api/routes/agents.py
nivora_ai/api/routes/deployment.py
nivora_ai/api/routes/monetization.py
nivora_ai/api/routes/monitoring.py
nivora_ai/core/__init__.py
nivora_ai/core/agent.py
nivora_ai/core/blockchain.py
nivora_ai/core/deployment.py
nivora_ai/core/interoperability.py
nivora_ai/core/monetization.py
nivora_ai/database/__init__.py
nivora_ai/database/models.py
nivora_ai/database/schemas.py
nivora_ai/networks/__init__.py
nivora_ai/networks/bsc.py
nivora_ai/networks/ethereum.py
nivora_ai/networks/polygon.py
nivora_ai/networks/solana.py
nivora_ai/utils/__init__.py
nivora_ai/utils/config.py
nivora_ai/utils/exceptions.py
nivora_ai/utils/logger.py
nivora_ai-1.0.0.dist-info/licenses/LICENSE
nivora_ai-1.0.0.dist-info/METADATA
nivora_ai-1.0.0.dist-info/WHEEL
nivora_ai-1.0.0.dist-info/entry_points.txt
nivora_ai-1.0.0.dist-info/top_level.txt
nivora_ai-1.0.0.dist-info/RECORD
