Metadata-Version: 2.4
Name: nivora-ai
Version: 1.0.0
Summary: Comprehensive Python SDK for deploying, scaling, and monetizing AI agents across multiple blockchain networks
Author-email: Nivora AI Team <support@nivora-ai.com>
Maintainer-email: Nivora AI Team <support@nivora-ai.com>
License: MIT
Project-URL: Homepage, https://nivora-ai.com
Project-URL: Documentation, https://docs.app-nivoraai.com
Project-URL: Repository, https://github.com/Nivora-AI/nivora-ai
Project-URL: Issues, https://github.com/Nivora-AI/nivora-ai/issues
Project-URL: Changelog, https://github.com/Nivora-AI/nivora-ai/releases
Keywords: ai,blockchain,agent,deployment,ethereum,polygon,solana,defi,cross-chain,monetization
Classifier: Development Status :: 5 - Production/Stable
Classifier: Intended Audience :: Developers
Classifier: License :: OSI Approved :: MIT License
Classifier: Operating System :: OS Independent
Classifier: Programming Language :: Python :: 3
Classifier: Programming Language :: Python :: 3.8
Classifier: Programming Language :: Python :: 3.9
Classifier: Programming Language :: Python :: 3.10
Classifier: Programming Language :: Python :: 3.11
Classifier: Programming Language :: Python :: 3.12
Classifier: Topic :: Software Development :: Libraries :: Python Modules
Classifier: Topic :: Internet :: WWW/HTTP :: HTTP Servers
Classifier: Topic :: Office/Business :: Financial
Classifier: Topic :: Scientific/Engineering :: Artificial Intelligence
Requires-Python: >=3.8.1
License-File: LICENSE
Requires-Dist: fastapi>=0.100.0
Requires-Dist: uvicorn[standard]>=0.20.0
Requires-Dist: pydantic>=2.0.0
Requires-Dist: web3>=6.0.0
Requires-Dist: aiohttp>=3.8.0
Requires-Dist: asyncpg>=0.28.0
Requires-Dist: sqlalchemy>=2.0.0
Requires-Dist: celery>=5.3.0
Requires-Dist: redis>=4.5.0
Requires-Dist: python-jose[cryptography]>=3.3.0
Requires-Dist: passlib[bcrypt]>=1.7.4
Requires-Dist: python-multipart>=0.0.6
Requires-Dist: websockets>=11.0.0
Provides-Extra: dev
Requires-Dist: pytest>=7.0.0; extra == "dev"
Requires-Dist: pytest-asyncio>=0.21.0; extra == "dev"
Requires-Dist: black>=23.0.0; extra == "dev"
Requires-Dist: flake8>=6.0.0; extra == "dev"
Requires-Dist: mypy>=1.0.0; extra == "dev"
Requires-Dist: pre-commit>=3.0.0; extra == "dev"
Provides-Extra: solana
Requires-Dist: solders>=0.18.0; extra == "solana"
Requires-Dist: solana>=0.30.0; extra == "solana"
Provides-Extra: analytics
Requires-Dist: pandas>=2.0.0; extra == "analytics"
Requires-Dist: numpy>=1.24.0; extra == "analytics"
Requires-Dist: matplotlib>=3.7.0; extra == "analytics"
Dynamic: license-file
